takt/__info__.py
takt/__init__.py
takt/__main__.py
takt/audio.py
takt/bot.py
takt/config.py
takt/error.py
takt/exceptions.py
takt/receivers/__init__.py
takt/receivers/client.py
takt/receivers/slash.py
takt/takt.py
takt-1.0.dist-info/LICENSE
takt-1.0.dist-info/METADATA
takt-1.0.dist-info/WHEEL
takt-1.0.dist-info/entry_points.txt
takt-1.0.dist-info/RECORD
