Metadata-Version: 2.1
Name: takt
Version: 1.0
Summary: Power your discord calls with music 🎐
Home-page: https://github.com/Animenosekai/takt
License: MIT
Keywords: animenosekai,takt,discord,bot,music,youtube
Author: Animenosekai
Author-email: animenosekai.mail@gmail.com
Maintainer: Animenosekai
Maintainer-email: animenosekai.mail@gmail.com
Requires-Python: >=3.8,<4.0
Classifier: Development Status :: 5 - Production/Stable
Classifier: Environment :: Console
Classifier: Intended Audience :: End Users/Desktop
Classifier: License :: OSI Approved :: MIT License
Classifier: Operating System :: OS Independent
Classifier: Programming Language :: Python
Classifier: Programming Language :: Python :: 3
Classifier: Programming Language :: Python :: 3.8
Classifier: Programming Language :: Python :: 3.9
Classifier: Programming Language :: Python :: 3.10
Classifier: Programming Language :: Python :: 3.11
Classifier: Topic :: Communications
Classifier: Topic :: Multimedia :: Sound/Audio
Classifier: Topic :: Multimedia :: Sound/Audio :: Players
Requires-Dist: PyNaCl (>=1.4,<2.0)
Requires-Dist: discord-py-slash-command (==3.0.3)
Requires-Dist: discord.py[voice] (>=1.7,<2.0)
Requires-Dist: nasse (>=2,<3)
Requires-Dist: youtube_dl (==2021.12.17)
Requires-Dist: yt-dlp (==2023.3.3)
Project-URL: Documentation, https://github.com/Animenosekai/takt/blob/main/README.md
Project-URL: Issue Tracker, https://github.com/Animenosekai/takt/issues
Project-URL: Repository, https://github.com/Animenosekai/takt
